{"json_data":{"standard":[{"exclude_unit_test":false,"plainword":"environment","patternword":null,"fullword":"environment","sound_file_name":"WORD_environment.mp3"},{"exclude_unit_test":false,"plainword":"biodegradable","patternword":null,"fullword":"biodegradable","sound_file_name":"WORD_biodegradable.mp3"},{"exclude_unit_test":false,"plainword":"technologies","patternword":null,"fullword":"technologies","sound_file_name":"WORD_technologies.mp3"},{"exclude_unit_test":false,"plainword":"recycled","patternword":null,"fullword":"recycled","sound_file_name":"WORD_recycled.mp3"},{"exclude_unit_test":false,"plainword":"energy consumption","patternword":null,"fullword":"energy consumption","sound_file_name":"WORD_energy_consumption.mp3"},{"exclude_unit_test":false,"plainword":"locality","patternword":null,"fullword":"locality","sound_file_name":"WORD_locality.mp3"},{"exclude_unit_test":false,"plainword":"synthetic","patternword":null,"fullword":"synthetic","sound_file_name":"WORD_synthetic.mp3"},{"exclude_unit_test":false,"plainword":"natural materials","patternword":null,"fullword":"natural materials","sound_file_name":"WORD_natural_materials.mp3"},{"exclude_unit_test":false,"plainword":"sustainable","patternword":null,"fullword":"sustainable","sound_file_name":"WORD_sustainable.mp3"},{"exclude_unit_test":false,"plainword":"reduce","patternword":null,"fullword":"reduce","sound_file_name":"WORD_reduce.mp3"}],"wordlist":{"settings":"{\"InOrder\":\"0\",\"DisablePhonics\":\"0\",\"StartPhonics\":\"0\",\"Nonsense\":\"0\",\"Homophones\":\"0\",\"ForcePhonics\":\"0\"}","ap_priority":0,"game_category_id":2,"available_games":[{"gameId":"2"},{"gameId":"22"},{"gameId":"3"},{"gameId":"20"},{"gameId":"23"},{"gameId":"5"},{"gameId":"25"},{"gameId":"26"},{"gameId":"30"},{"gameId":"76"},{"gameId":"38"},{"gameId":"28"},{"gameId":"75"},{"gameId":"16"},{"gameId":"17"}],"description":null,"exclude_ap":"0","is_revisionlist":0,"exclude_unittest":"0","suggested_games":[{"gameId":"2"},{"gameId":"23"},{"gameId":"16"},{"gameId":"5"},{"gameId":"22"},{"gameId":"26"},{"gameId":"76"},{"gameId":"75"}],"has_standard":true,"has_extended":false,"name":"Sustainability","game_settings":null,"is_unit_revision":0,"unit_id":8781,"wl_order":0},"sentences":{"selects":[{"select_count":1,"desktopSelectIndex":11}],"top":{"select_count":1,"group_type":"GROUPSELECT"},"references":[{"desktopSelectIndex":11,"sentences":[{"sentence":"The manufacture, the use and the disposing of products|can each have a negative effect on the *.","desktopSelectIndex":1,"rightWords":[{"plainword":"environment"}],"soundPeep":"SENT_environment_11.mp3"},{"sentence":"Use * materials which decay quickly if|they need to be thrown away.","desktopSelectIndex":1,"rightWords":[{"plainword":"biodegradable"}],"soundPeep":"SENT_biodegradable.mp3"},{"sentence":"Green * can help the planet against climate change.","desktopSelectIndex":1,"rightWords":[{"plainword":"technologies"}],"soundPeep":"SENT_technologies.mp3"},{"sentence":"Can your product be made from * materials,|be easily repaired, and be recycled after use?","desktopSelectIndex":1,"rightWords":[{"plainword":"recycled"}],"soundPeep":"SENT_recycled_5.mp3"},{"sentence":"Think about the technologies and *|your product involves in its construction and use.","desktopSelectIndex":1,"rightWords":[{"plainword":"energy consumption"}],"soundPeep":"SENT_energy_consumption.mp3"},{"sentence":"Does the * of materials needed for your product|mean they have to travel too far?","desktopSelectIndex":1,"rightWords":[{"plainword":"locality"}],"soundPeep":"SENT_locality.mp3"},{"sentence":"Plastic is an example of a * material that|has valuable properties but can cause pollution at|all stages of its life cycle.","desktopSelectIndex":1,"rightWords":[{"plainword":"synthetic"}],"soundPeep":"SENT_synthetic_2.mp3"},{"sentence":"Wood and cotton are examples of *|but their production needs very careful management.","desktopSelectIndex":1,"rightWords":[{"plainword":"natural materials"}],"soundPeep":"SENT_natural_materials.mp3"},{"sentence":"* design aims to minimise or have no negative|impact on the environment.","desktopSelectIndex":1,"rightWords":[{"plainword":"sustainable"}],"soundPeep":"SENT_sustainable_3.mp3"},{"sentence":"Is there a way you can * the amount of material|and energy you use to produce your product?","desktopSelectIndex":1,"rightWords":[{"plainword":"reduce"}],"soundPeep":"SENT_reduce.mp3"}]}]}}}
