{"json_data":{"standard":[{"photo_image_file_name":"IPHOTO_pen_2.png","exclude_unit_test":false,"wordshark_image_file_name":"IWS_pen_2.png","split_sound_file_names":["SOUND_p.mp3","SOUND_e.mp3","SOUND_n.mp3","WORD_pen.mp3"],"plainword":"pen","patternword":null,"fullword":"p·e·n=p·e·n","sound_file_name":"WORD_pen.mp3"},{"photo_image_file_name":"IPHOTO_paper_2.png","exclude_unit_test":false,"wordshark_image_file_name":"IWS_paper_2.png","split_sound_file_names":["SOUND_p.mp3","SOUND_ay.mp3","PSYL_p_ay.mp3","SOUND_p.mp3","SOUND_eu.mp3","PSYL_p_eu.mp3","WORD_paper.mp3"],"plainword":"paper","patternword":null,"fullword":"p·a·p·er=p·ay·\/p·eu","sound_file_name":"WORD_paper.mp3"},{"photo_image_file_name":"IPHOTO_pencil_2.png","exclude_unit_test":false,"wordshark_image_file_name":"IWS_pencil_2.png","split_sound_file_names":["SOUND_p.mp3","SOUND_e.mp3","SOUND_n.mp3","PSYL_p_e_n.mp3","SOUND_s.mp3","SOUND_l.mp3","PSYL_s_l.mp3","WORD_pencil.mp3"],"plainword":"pencil","patternword":null,"fullword":"p·e·n·c·il=p·e·n·\/s·l","sound_file_name":"WORD_pencil.mp3"},{"photo_image_file_name":"IPHOTO_scissors_2.png","exclude_unit_test":false,"wordshark_image_file_name":"IWS_scissors_2.png","split_sound_file_names":["SOUND_s.mp3","SOUND_i.mp3","SOUND_z.mp3","PSYL_s_i_z.mp3","SOUND_er.mp3","SOUND_z.mp3","PSYL_er_z.mp3","WORD_scissors.mp3"],"plainword":"scissors","patternword":null,"fullword":"sc·i·ss·or·s=s·i·z·\/er·z","sound_file_name":"WORD_scissors.mp3"},{"photo_image_file_name":"IPHOTO_ruler.png","exclude_unit_test":false,"wordshark_image_file_name":"IWS_ruler.png","split_sound_file_names":["SOUND_r.mp3","SOUND_oo.mp3","SOUND_l.mp3","PSYL_r_oo_l.mp3","SOUND_eu.mp3","PSYL_eu.mp3","WORD_ruler.mp3"],"plainword":"ruler","patternword":null,"fullword":"r·u·l·er=r·oo·l·\/eu","sound_file_name":"WORD_ruler.mp3"}],"wordlist":{"settings":"{\"InOrder\":\"0\",\"DisablePhonics\":\"0\",\"StartPhonics\":\"0\",\"Nonsense\":\"0\",\"Homophones\":\"0\",\"ForcePhonics\":\"0\"}","ap_priority":0,"game_category_id":2,"available_games":[{"gameId":"70"},{"gameId":"71"},{"gameId":"72"},{"gameId":"74"},{"gameId":"1"},{"gameId":"4"},{"gameId":"24"},{"gameId":"6"},{"gameId":"2"},{"gameId":"22"},{"gameId":"3"},{"gameId":"20"},{"gameId":"23"},{"gameId":"5"},{"gameId":"25"},{"gameId":"26"},{"gameId":"30"},{"gameId":"76"},{"gameId":"38"},{"gameId":"28"},{"gameId":"75"},{"gameId":"17"}],"description":"Basic vocabulary - more for understanding rather than for spelling.","exclude_ap":"0","is_revisionlist":0,"exclude_unittest":"0","suggested_games":[{"gameId":"1"},{"gameId":"4"},{"gameId":"23"},{"gameId":"22"},{"gameId":"26"}],"has_standard":true,"has_extended":false,"name":"classroom words 2","game_settings":null,"is_unit_revision":0,"unit_id":8789,"wl_order":0}}}
