<?xml version="1.0" encoding="UTF-8" standalone="no"?><root><Topic AllOrNone="0" AllowHomophones="1" AllowPairs="0" ApNotInTest="0" ApNotInUnitOrTest="0" ApPriority="0" FL="0" InOrder="0" IsBlended="0" IsRevision="0" PhonicOffGames="dummy_pg_off" PhonicOnGames="dummy_pg_on" PhonicSounds="0" PhonicWords="1" RecommendedPhonicOffGames="dummy_rpg_off" RecommendedPhonicOnGames="dummy_rpg_on" SplitOffGames="dummy_sg_off" SplitOnGames="dummy_sg_on" TopicGameCategoryTypes="Whole words|Focus on phonics" TopicName="-are" TopicTeachingNote="££i**2****2**££b**2****2**-are££/b**2****2**££/i**2****2** is an alternative spelling to ££i**2****2**££b**2****2**air££/b**2****2**££/i**2****2**. Note the homophones." TopicUUID="58793"/><TopicBlocks><TopicBlock TBType="TOPICBLOCKSTANDARD"><References><Reference/></References></TopicBlock><TopicBlock TBType="TOPICBLOCKSTANDARD"><References><Reference/></References></TopicBlock><TopicBlock TBType="TOPICBLOCKSTANDARD"><References><Reference/></References></TopicBlock><TopicBlock TBType="TOPICBLOCKSTANDARD"><References><Reference/></References></TopicBlock><TopicBlock TBType="TOPICBLOCKSTANDARD"><References><Reference/></References></TopicBlock><TopicBlock TBType="TOPICBLOCKSTANDARD"><References><Reference/></References></TopicBlock><TopicBlock TBType="TOPICBLOCKSTANDARD"><References><Reference/></References></TopicBlock><TopicBlock TBType="TOPICBLOCKSTANDARD"><References><Reference/></References></TopicBlock><TopicBlock TBType="TOPICBLOCKEXTENDED"><Select0 SelectNo0="8"><Select1 SelectNo1="6"><References1 WordIDs="3194538,3194539,3194540,3194541,3194542,3194543,3194544,3194545"><Reference IsWordTarget="1" RefType="0" WordID="3194538"/><Reference IsWordTarget="1" RefType="0" WordID="3194539"/><Reference IsWordTarget="1" RefType="0" WordID="3194540"/><Reference IsWordTarget="1" RefType="0" WordID="3194541"/><Reference IsWordTarget="1" RefType="0" WordID="3194542"/><Reference IsWordTarget="1" RefType="0" WordID="3194543"/><Reference IsWordTarget="1" RefType="0" WordID="3194544"/><Reference IsWordTarget="1" RefType="0" WordID="3194545"/></References1></Select1><Select1 SelectNo1="3"><References1 WordIDs="3194546,3194547,3194548"><Reference IsWordTarget="1" RefType="0" WordID="3194546"/><Reference IsWordTarget="1" RefType="0" WordID="3194547"/><Reference IsWordTarget="1" RefType="0" WordID="3194548"/></References1></Select1></Select0></TopicBlock><TopicBlock GameBlockType="SENTENCE" TBType="TOPICBLOCKGAME"><Game GameCategory="TOPICMAINCATEGORY_NONPHONICS" GameName="Sentence crossword" IsGameHeading="0"/><Sentences><Sentence RecName="SENT_care.mp3" SentenceText="I often have to * for my baby brother."><Targets><Target WordID="3194549"/></Targets></Sentence><Sentence RecName="SENT_fare.mp3" SentenceText="I forgot my bus * so I have to walk."><Targets><Target WordID="3194550"/></Targets></Sentence><Sentence RecName="SENT_scare_2.mp3" SentenceText="He tries to * me with scary stories."><Targets><Target WordID="3194551"/></Targets></Sentence><Sentence RecName="SENT_stare.mp3" SentenceText="It is rude to point or * at people."><Targets><Target WordID="3194552"/></Targets></Sentence><Sentence RecName="SENT_share.mp3" SentenceText="We will * the cake between us."><Targets><Target WordID="3194553"/></Targets></Sentence><Sentence RecName="SENT_hare_2.mp3" SentenceText="A * runs much faster than a rabbit."><Targets><Target WordID="3194554"/></Targets></Sentence><Sentence RecName="SENT_rare.mp3" SentenceText="It is very * to see a mole."><Targets><Target WordID="3194555"/></Targets></Sentence><Sentence RecName="SENT_bare_2.mp3" SentenceText="The trees are * in winter."><Targets><Target WordID="3194556"/></Targets></Sentence></Sentences></TopicBlock><TopicBlock GameBlockType="PATTERN" TBType="TOPICBLOCKGAME"><Game GameCategory="TOPICMAINCATEGORY_NONPHONICS" GameName="Pattern" IsGameHeading="0"/><Select0><Select1 HeadingSoundUUID="TOPIC_find_are.mp3" HeadingText="find -[are]"><References1 SelectNo="15" WordIDs="3194557,3194558,3194559,3194560,3194561,3194562,3194563,3194564,3194565,3194566,3194557,3194558,3194559,3194560,3194561,3194562,3194563,3194564,3194565,3194566"/></Select1><Select1 HeadingText="No"><References1 SelectNo="15" WordIDs="3194548,3194567,3194568,3194569,3194570,3194571,3194572,3194573,3194574,3194575,3194576,3194577,3194578,3194579,3194580,3194581,3194582,3194583,3194584,3194585,3194586,3194587,3194588,3194589,3194590,3194591,3194592,3194593,3194594,3194595,3194596,3194597"/></Select1></Select0></TopicBlock><TopicBlock GameBlockType="HELICOPTERLISTEN" TBType="TOPICBLOCKGAME"><Game GameCategory="TOPICMAINCATEGORY_NONPHONICS" GameName="Helicopter (listen)" IsGameHeading="0"/><Select0><Select1 HeadingSoundUUID="TOPIC_hear_are_as_in_care.mp3" HeadingText="Hear -[are] as in c[are]"><References1 SelectNo="8" WordIDs="3194557,3194558,3194559,3194560,3194561,3194562,3194563,3194564,3194565,3194566"/></Select1><Select1 HeadingSoundUUID="TOPIC_no.mp3" HeadingText="No"><References1 SelectNo="6" WordIDs="3194567,3194568,3194569,3194570,3194571,3194572,3194573,3194574,3194598,3194599,3194600,3194575,3194576,3194577,3194578,3194579,3194580,3194581,3194582,3194583,3194601,3194602,3194603,3194604,3194605,3194606,3194607,3194608,3194609,3194610,3194611,3194584,3194612,3194586,3194587,3194588,3194589,3194613,3194614,3194615,3194616,3194590,3194591,3194592,3194593,3194594,3194595,3194596,3194597,3194617,3194618,3194619,3194620,3194621,3194548"/></Select1></Select0></TopicBlock></TopicBlocks></root>
