<?xml version="1.0" encoding="UTF-8" standalone="no"?><root><Topic AllOrNone="0" AllowHomophones="1" AllowPairs="0" ApNotInTest="0" ApNotInUnitOrTest="0" ApPriority="0" FL="0" InOrder="0" IsBlended="0" IsRevision="0" PhonicOffGames="dummy_pg_off" PhonicOnGames="dummy_pg_on" PhonicSounds="0" PhonicWords="1" RecommendedPhonicOffGames="dummy_rpg_off" RecommendedPhonicOnGames="dummy_rpg_on" SplitOffGames="dummy_sg_off" SplitOnGames="dummy_sg_on" TopicGameCategoryTypes="Whole words|Focus on phonics" TopicName="long/short vowel - choose k or ck" TopicTeachingNote="Listen for the long vowel/short vowel. The ££i**2****2**££b**2****2**ck££/b**2****2**££/i**2****2** spelling is only used following the short vowel sound." TopicUUID="58797"/><TopicBlocks><TopicBlock TBType="TOPICBLOCKSTANDARD"><References><Reference/></References></TopicBlock><TopicBlock TBType="TOPICBLOCKSTANDARD"><References><Reference/></References></TopicBlock><TopicBlock TBType="TOPICBLOCKSTANDARD"><References><Reference/></References></TopicBlock><TopicBlock TBType="TOPICBLOCKSTANDARD"><References><Reference/></References></TopicBlock><TopicBlock TBType="TOPICBLOCKSTANDARD"><References><Reference/></References></TopicBlock><TopicBlock TBType="TOPICBLOCKSTANDARD"><References><Reference/></References></TopicBlock><TopicBlock TBType="TOPICBLOCKSTANDARD"><References><Reference/></References></TopicBlock><TopicBlock TBType="TOPICBLOCKSTANDARD"><References><Reference/></References></TopicBlock><TopicBlock TBType="TOPICBLOCKSTANDARD"><References><Reference/></References></TopicBlock><TopicBlock TBType="TOPICBLOCKSTANDARD"><References><Reference/></References></TopicBlock><TopicBlock TBType="TOPICBLOCKEXTENDED"><Select0 SelectNo0="8"><Select1 SelectNo1="2"><References1 AllOrNones="1" WordIDs="3194758,3194759"><Reference AllOrNone="0" AllOrNoneIndex="0" IsWordTarget="1" RefType="0" WordID="3194758"/><Reference AllOrNone="0" AllOrNoneIndex="1" IsWordTarget="1" RefType="0" WordID="3194759"/></References1><References1 AllOrNones="1" WordIDs="3194760,3194761"><Reference AllOrNone="1" AllOrNoneIndex="0" IsWordTarget="1" RefType="0" WordID="3194760"/><Reference AllOrNone="1" AllOrNoneIndex="1" IsWordTarget="1" RefType="0" WordID="3194761"/></References1><References1 AllOrNones="1" WordIDs="3194762,3194763"><Reference AllOrNone="2" AllOrNoneIndex="0" IsWordTarget="1" RefType="0" WordID="3194762"/><Reference AllOrNone="2" AllOrNoneIndex="1" IsWordTarget="1" RefType="0" WordID="3194763"/></References1><References1 AllOrNones="1" WordIDs="3194764,3194765"><Reference AllOrNone="3" AllOrNoneIndex="0" IsWordTarget="1" RefType="0" WordID="3194764"/><Reference AllOrNone="3" AllOrNoneIndex="1" IsWordTarget="1" RefType="0" WordID="3194765"/></References1><References1 AllOrNones="1" WordIDs="3194766,3194767"><Reference AllOrNone="4" AllOrNoneIndex="0" IsWordTarget="1" RefType="0" WordID="3194766"/><Reference AllOrNone="4" AllOrNoneIndex="1" IsWordTarget="1" RefType="0" WordID="3194767"/></References1></Select1><Select1 SelectNo1="8"><References1 AllOrNones="1" WordIDs="3194768,3194769"><Reference AllOrNone="0" AllOrNoneIndex="0" IsWordTarget="1" RefType="0" WordID="3194768"/><Reference AllOrNone="0" AllOrNoneIndex="1" IsWordTarget="1" RefType="0" WordID="3194769"/></References1><References1 AllOrNones="1" WordIDs="3194770,3194771"><Reference AllOrNone="1" AllOrNoneIndex="0" IsWordTarget="1" RefType="0" WordID="3194770"/><Reference AllOrNone="1" AllOrNoneIndex="1" IsWordTarget="1" RefType="0" WordID="3194771"/></References1><References1 AllOrNones="1" WordIDs="3194772,3194773"><Reference AllOrNone="2" AllOrNoneIndex="0" IsWordTarget="1" RefType="0" WordID="3194772"/><Reference AllOrNone="2" AllOrNoneIndex="1" IsWordTarget="1" RefType="0" WordID="3194773"/></References1><References1 AllOrNones="1" WordIDs="3194774,3194775"><Reference AllOrNone="3" AllOrNoneIndex="0" IsWordTarget="1" RefType="0" WordID="3194774"/><Reference AllOrNone="3" AllOrNoneIndex="1" IsWordTarget="1" RefType="0" WordID="3194775"/></References1><References1 AllOrNones="1" WordIDs="3194776,3194777"><Reference AllOrNone="4" AllOrNoneIndex="0" IsWordTarget="1" RefType="0" WordID="3194776"/><Reference AllOrNone="4" AllOrNoneIndex="1" IsWordTarget="1" RefType="0" WordID="3194777"/></References1></Select1></Select0></TopicBlock><TopicBlock GameBlockType="HELICOPTERLISTEN" TBType="TOPICBLOCKGAME"><Game GameCategory="TOPICMAINCATEGORY_NONPHONICS" GameName="Helicopter (listen)" IsGameHeading="0"/><Select0><Select1 HeadingSoundUUID="TOPIC_hear_short_vowel_2.mp3" HeadingText="Hear short vowel"><References1 SelectNo="7" WordIDs="3194778,3194779,3194780,3194781,3194782,3194783,3194784,3194785,3194786,3194776"/></Select1><Select1 HeadingSoundUUID="TOPIC_hear_long_vowel_2.mp3" HeadingText="Hear long vowel"><References1 SelectNo="6" WordIDs="3194787,3194788,3194789,3194790,3194791,3194792,3194793,3194794,3194795,3194777"/></Select1></Select0></TopicBlock><TopicBlock GameBlockType="SENTENCE" TBType="TOPICBLOCKGAME"><Game GameCategory="TOPICMAINCATEGORY_NONPHONICS" GameName="Sentence crossword" IsGameHeading="0"/><Sentences><Sentence RecName="SENT_back.mp3" SentenceText="Come * here."><Targets><Target WordID="3194796"/></Targets></Sentence><Sentence RecName="SENT_bake.mp3" SentenceText="I will * a cake."><Targets><Target WordID="3194797"/></Targets></Sentence><Sentence RecName="SENT_snack.mp3" SentenceText="Do we need a * before lunch?"><Targets><Target WordID="3194798"/></Targets></Sentence><Sentence RecName="SENT_snake_3.mp3" SentenceText="The * lay coiled in the sun."><Targets><Target WordID="3194799"/></Targets></Sentence><Sentence RecName="SENT_clock_3.mp3" SentenceText="This * shows the wrong time."><Targets><Target WordID="3194800"/></Targets></Sentence><Sentence RecName="SENT_cloak_2.mp3" SentenceText="The princess wore a velvet *."><Targets><Target WordID="3194801"/></Targets></Sentence><Sentence RecName="SENT_peck.mp3" SentenceText="The hen likes to * up food."><Targets><Target WordID="3194802"/></Targets></Sentence><Sentence RecName="SENT_peak.mp3" SentenceText="There is snow on that mountain *."><Targets><Target WordID="3194803"/></Targets></Sentence><Sentence RecName="SENT_lick_2.mp3" SentenceText="I * my ice-cream so that it does not drip."><Targets><Target WordID="3194804"/></Targets></Sentence><Sentence RecName="SENT_like_4.mp3" SentenceText="I * my job."><Targets><Target WordID="3194805"/></Targets></Sentence></Sentences></TopicBlock></TopicBlocks></root>
