<?xml version="1.0" encoding="UTF-8" standalone="no"?><root><Topic AllOrNone="0" AllowHomophones="1" AllowPairs="0" ApNotInTest="0" ApNotInUnitOrTest="0" ApPriority="1" FL="0" InOrder="0" IsBlended="0" IsRevision="0" PhonicOffGames="dummy_pg_off" PhonicOnGames="dummy_pg_on" PhonicSounds="0" PhonicWords="1" RecommendedPhonicOffGames="dummy_rpg_off" RecommendedPhonicOnGames="dummy_rpg_on" SplitOffGames="dummy_sg_off" SplitOnGames="dummy_sg_on" TopicGameCategoryTypes="Whole words|Focus on phonics" TopicName="oa, ow, o-e mixed" TopicTeachingNote="Alternative spellings for a ££b**2****2**long££/b**2****2** ££i**2****2**££b**2****2** o££/b**2****2**££/i**2****2** sound in one syllable words. There is no help from the sound as to which spelling is used. A memory for these, is developed by seeing the words in print and in context many times, and by practising writing and typing them. The ££i**2****2**££b**2****2**helicopter-spell££/b**2****2**££/i**2****2** game is good for sorting them. The number of words in each column reflects the frequency each spelling is likely to occur. Reminder - each time you click on the ££b**2****2**Extended Sample££/b**2****2** tab (top right), you get a new selection of words." TopicUUID="58759"/><TopicBlocks><TopicBlock TBType="TOPICBLOCKSTANDARD"><References><Reference/></References></TopicBlock><TopicBlock TBType="TOPICBLOCKSTANDARD"><References><Reference/></References></TopicBlock><TopicBlock TBType="TOPICBLOCKSTANDARD"><References><Reference/></References></TopicBlock><TopicBlock TBType="TOPICBLOCKSTANDARD"><References><Reference/></References></TopicBlock><TopicBlock TBType="TOPICBLOCKSTANDARD"><References><Reference/></References></TopicBlock><TopicBlock TBType="TOPICBLOCKSTANDARD"><References><Reference/></References></TopicBlock><TopicBlock TBType="TOPICBLOCKSTANDARD"><References><Reference/></References></TopicBlock><TopicBlock TBType="TOPICBLOCKSTANDARD"><References><Reference/></References></TopicBlock><TopicBlock TBType="TOPICBLOCKEXTENDED"><Select0 SelectNo0="8"><Select1 SelectNo1="1"><References1 WordIDs="3191939,3191940,3191941,3191942,3191943,3191944,3191945,3191946"><Reference IsWordTarget="1" RefType="0" WordID="3191939"/><Reference IsWordTarget="1" RefType="0" WordID="3191940"/><Reference IsWordTarget="1" RefType="0" WordID="3191941"/><Reference IsWordTarget="1" RefType="0" WordID="3191942"/><Reference IsWordTarget="1" RefType="0" WordID="3191943"/><Reference IsWordTarget="1" RefType="0" WordID="3191944"/><Reference IsWordTarget="1" RefType="0" WordID="3191945"/><Reference IsWordTarget="1" RefType="0" WordID="3191946"/></References1></Select1><Select1 SelectNo1="4"><References1 WordIDs="3191947,3191948,3191945,3191949,3191950,3191951,3191952,3191946,3191947,3191945,3191952,3191953,3191951,3191954,3191944,3191955,3191956"><Reference IsWordTarget="1" RefType="0" WordID="3191947"/><Reference IsWordTarget="1" RefType="0" WordID="3191948"/><Reference IsWordTarget="1" RefType="0" WordID="3191945"/><Reference IsWordTarget="1" RefType="0" WordID="3191949"/><Reference IsWordTarget="1" RefType="0" WordID="3191950"/><Reference IsWordTarget="1" RefType="0" WordID="3191951"/><Reference IsWordTarget="1" RefType="0" WordID="3191952"/><Reference IsWordTarget="1" RefType="0" WordID="3191946"/><Reference IsWordTarget="1" RefType="0" WordID="3191947"/><Reference IsWordTarget="1" RefType="0" WordID="3191945"/><Reference IsWordTarget="1" RefType="0" WordID="3191952"/><Reference IsWordTarget="1" RefType="0" WordID="3191953"/><Reference IsWordTarget="1" RefType="0" WordID="3191951"/><Reference IsWordTarget="1" RefType="0" WordID="3191954"/><Reference IsWordTarget="1" RefType="0" WordID="3191944"/><Reference IsWordTarget="1" RefType="0" WordID="3191955"/><Reference IsWordTarget="1" RefType="0" WordID="3191956"/></References1></Select1><Select1 SelectNo1="2"><References1 WordIDs="3191939,3191957,3191958,3191959,3191960,3191961,3191962,3191963"><Reference IsWordTarget="1" RefType="0" WordID="3191939"/><Reference IsWordTarget="1" RefType="0" WordID="3191957"/><Reference IsWordTarget="1" RefType="0" WordID="3191958"/><Reference IsWordTarget="1" RefType="0" WordID="3191959"/><Reference IsWordTarget="1" RefType="0" WordID="3191960"/><Reference IsWordTarget="1" RefType="0" WordID="3191961"/><Reference IsWordTarget="1" RefType="0" WordID="3191962"/><Reference IsWordTarget="1" RefType="0" WordID="3191963"/></References1></Select1><Select1 SelectNo1="2"><References1 WordIDs="3191964,3191941,3191965,3191966,3191967,3191968,3191942,3191969,3191967,3191943,3191968,3191970,3191941,3191971,3191969,3191972"><Reference IsWordTarget="1" RefType="0" WordID="3191964"/><Reference IsWordTarget="1" RefType="0" WordID="3191941"/><Reference IsWordTarget="1" RefType="0" WordID="3191965"/><Reference IsWordTarget="1" RefType="0" WordID="3191966"/><Reference IsWordTarget="1" RefType="0" WordID="3191967"/><Reference IsWordTarget="1" RefType="0" WordID="3191968"/><Reference IsWordTarget="1" RefType="0" WordID="3191942"/><Reference IsWordTarget="1" RefType="0" WordID="3191969"/><Reference IsWordTarget="1" RefType="0" WordID="3191967"/><Reference IsWordTarget="0" RefType="0" WordID="3191943"/><Reference IsWordTarget="1" RefType="0" WordID="3191968"/><Reference IsWordTarget="0" RefType="0" WordID="3191970"/><Reference IsWordTarget="1" RefType="0" WordID="3191941"/><Reference IsWordTarget="0" RefType="0" WordID="3191971"/><Reference IsWordTarget="1" RefType="0" WordID="3191969"/><Reference IsWordTarget="0" RefType="0" WordID="3191972"/></References1></Select1></Select0></TopicBlock><TopicBlock GameBlockType="HELICOPTERSPELL" TBType="TOPICBLOCKGAME"><Game GameCategory="TOPICMAINCATEGORY_NONPHONICS" GameName="Helicopter (spell)" IsGameHeading="0"/><Select0><Select1 HeadingText="-[o]-[e]"><References1 SelectNo="6" WordIDs="3191973,3191974,3191975,3191976,3191977,3191978,3191979,3191980,3191981,3191982,3191983,3191984,3191985,3191986,3191987,3191988,3191989,3191990,3191991,3191992,3191993,3191994,3191995,3191996,3191997,3191998,3191999,3192000,3192001,3192002,3192003"/></Select1><Select1 HeadingText="-[oa]-"><References1 SelectNo="3" WordIDs="3192004,3192005,3192006,3192007,3192008,3192009,3192010,3192011,3192012,3192013,3192014,3192015,3192016,3192017,3192018,3192019,3192020,3192021,3192022,3192023,3192024,3192025,3192026,3192027,3192028"/></Select1><Select1 HeadingText="-[ow]"><References1 SelectNo="3" WordIDs="3192029,3192030,3192031,3192032,3192033,3192034,3192035,3192036,3192037,3192038,3192039,3192040,3192041,3192042"/></Select1></Select0></TopicBlock><TopicBlock GameBlockType="SENTENCE" TBType="TOPICBLOCKGAME"><Game GameCategory="TOPICMAINCATEGORY_NONPHONICS" GameName="Sentence crossword" IsGameHeading="0"/><Sentences><Sentence RecName="SENT_boat_4.mp3" SentenceText="That is a huge fishing *."><Targets><Target WordID="3192043"/></Targets></Sentence><Sentence RecName="SENT_coat.mp3" SentenceText="I need a * for winter."><Targets><Target WordID="3192044"/></Targets></Sentence><Sentence RecName="SENT_grow_8.mp3" SentenceText="Tiny babies * fast."><Targets><Target WordID="3192045"/></Targets></Sentence><Sentence RecName="SENT_glow.mp3" SentenceText="I can see the fire *."><Targets><Target WordID="3192046"/></Targets></Sentence><Sentence RecName="SENT_shown.mp3" SentenceText="Have you * your ticket yet?"><Targets><Target WordID="3192047"/></Targets></Sentence><Sentence RecName="SENT_code.mp3" SentenceText="This message uses a secret *."><Targets><Target WordID="3192048"/></Targets></Sentence><Sentence RecName="SENT_stone_3.mp3" SentenceText="Do not throw that *."><Targets><Target WordID="3192049"/></Targets></Sentence><Sentence RecName="SENT_hope_6.mp3" SentenceText="I * you like my picture."><Targets><Target WordID="3192050"/></Targets></Sentence></Sentences></TopicBlock></TopicBlocks></root>
